copatrec/__init__.py
copatrec/copatrec.py
copatrec/constants/__init__.py
copatrec/constants/constants.py
copatrec/math/__init__.py
copatrec/math/patterns.py
copatrec/result/__init__.py
copatrec/result/result.py
copatrec-0.0.7.dist-info/LICENSE
copatrec-0.0.7.dist-info/METADATA
copatrec-0.0.7.dist-info/WHEEL
copatrec-0.0.7.dist-info/top_level.txt
copatrec-0.0.7.dist-info/RECORD
