Metadata-Version: 2.1
Name: copatrec
Version: 0.0.7
Summary: Correlation pattern recognizer (Copatrec), a package to find nonlinear patterns (regressions) using Machine Learning.
Author: Siamak Khatami
Author-email: <siamak.khatami@ntnu.no>
Classifier: Programming Language :: Python :: 3.6
Classifier: License :: Free for non-commercial use
Classifier: Operating System :: OS Independent
Requires-Python: >=3.6
License-File: LICENSE
Requires-Dist: pandas
Requires-Dist: numpy
Requires-Dist: matplotlib
Requires-Dist: scikit-learn
Requires-Dist: scipy
